ai_image_renamer/__init__.py
ai_image_renamer/cli.py
ai_image_renamer/renamer.py
ai_image_renamer/utils.py
ai_image_renamer-1.0.0.dist-info/licenses/LICENSE
ai_image_renamer-1.0.0.dist-info/METADATA
ai_image_renamer-1.0.0.dist-info/WHEEL
ai_image_renamer-1.0.0.dist-info/entry_points.txt
ai_image_renamer-1.0.0.dist-info/top_level.txt
ai_image_renamer-1.0.0.dist-info/RECORD
