Metadata-Version: 2.4
Name: ai-image-renamer
Version: 1.0.0
Summary: Rename images based on AI-generated descriptions.
Author-email: Kolja Nolte <kolja.nolte@gmail.com>
License-Expression: MIT
Project-URL: Homepage, https://docs.kolja-nolte.com/ai-image-renamer
Project-URL: Repository, https://gitlab.com/thaikolja/ai-image-renamer.git
Classifier: Development Status :: 4 - Beta
Classifier: Intended Audience :: Developers
Classifier: Programming Language :: Python :: 3
Classifier: Programming Language :: Python :: 3.8
Classifier: Programming Language :: Python :: 3.9
Classifier: Programming Language :: Python :: 3.10
Classifier: Programming Language :: Python :: 3.11
Classifier: Programming Language :: Python :: 3.12
Classifier: Topic :: Multimedia :: Graphics :: Graphics Conversion
Classifier: Topic :: Scientific/Engineering :: Image Processing
Requires-Python: >=3.8
License-File: LICENSE
Requires-Dist: filetype~=1.2.0
Requires-Dist: groq~=0.31.0
Requires-Dist: python-dotenv~=1.1.1
Provides-Extra: test
Requires-Dist: pytest; extra == "test"
Dynamic: license-file
